README.rst
setup.py
plypatch/__init__.py
plypatch/cli.py
plypatch/exc.py
plypatch/fixup_patch.py
plypatch/utils.py
plypatch/version.py
plypatch.egg-info/PKG-INFO
plypatch.egg-info/SOURCES.txt
plypatch.egg-info/dependency_links.txt
plypatch.egg-info/entry_points.txt
plypatch.egg-info/top_level.txt
plypatch/git/__init__.py
plypatch/git/exc.py
tests/functional/__init__.py
tests/functional/test_everything.py