Metadata-Version: 1.1
Name: plypatch
Version: 0.4.1
Summary: Ply: Git-based Patch Management
Home-page: https://github.com/rconradharris/ply
Author: Rick Harris
Author-email: rconradharris@gmail.com
License: MIT
Platform: UNKNOWN
Classifier: Development Status :: 4 - Beta
Classifier: License :: OSI Approved :: Apache Software License
Classifier: Operating System :: POSIX :: Linux
Classifier: Programming Language :: Python :: 2.6
